/*     */ package com.android.build.gradle.internal.res.namespaced;
/*     */ 
/*     */ import com.android.build.gradle.internal.core.GradleVariantConfiguration;
/*     */ import com.android.build.gradle.internal.scope.TaskConfigAction;
/*     */ import com.android.build.gradle.internal.scope.VariantScope;
/*     */ import java.io.File;
/*     */ import kotlin.Metadata;
/*     */ import kotlin.jvm.functions.Function0;
/*     */ import kotlin.jvm.internal.FunctionReference;
/*     */ import kotlin.jvm.internal.Reflection;
/*     */ import kotlin.reflect.KDeclarationContainer;
/*     */ import org.jetbrains.annotations.NotNull;
/*     */ import org.jetbrains.annotations.Nullable;
/*     */ 
/*     */ @Metadata(mv={1, 1, 9}, bv={1, 0, 2}, k=1, d1={"\0000\n\002\030\002\n\002\030\002\n\002\030\002\n\000\n\002\030\002\n\000\n\002\030\002\n\002\b\004\n\002\020\002\n\002\b\002\n\002\020\016\n\000\n\002\030\002\n\000\030\0002\b\022\004\022\0020\0020\001B'\022\006\020\003\032\0020\004\022\b\020\005\032\004\030\0010\006\022\006\020\007\032\0020\006\022\006\020\b\032\0020\006¢\006\002\020\tJ\020\020\n\032\0020\0132\006\020\f\032\0020\002H\026J\b\020\r\032\0020\016H\026J\016\020\017\032\b\022\004\022\0020\0020\020H\026R\020\020\005\032\004\030\0010\006X\004¢\006\002\n\000R\016\020\b\032\0020\006X\004¢\006\002\n\000R\016\020\003\032\0020\004X\004¢\006\002\n\000R\016\020\007\032\0020\006X\004¢\006\002\n\000¨\006\021"}, d2={"Lcom/android/build/gradle/internal/res/namespaced/LinkLibraryAndroidResourcesTask$ConfigAction;", "Lcom/android/build/gradle/internal/scope/TaskConfigAction;", "Lcom/android/build/gradle/internal/res/namespaced/LinkLibraryAndroidResourcesTask;", "scope", "Lcom/android/build/gradle/internal/scope/VariantScope;", "rClassSource", "Ljava/io/File;", "staticLibApk", "rDotTxt", "(Lcom/android/build/gradle/internal/scope/VariantScope;Ljava/io/File;Ljava/io/File;Ljava/io/File;)V", "execute", "", "task", "getName", "", "getType", "Ljava/lang/Class;", "gradle-core"})
/*     */ public final class LinkLibraryAndroidResourcesTask$ConfigAction
/*     */   implements TaskConfigAction<LinkLibraryAndroidResourcesTask>
/*     */ {
/*     */   private final VariantScope scope;
/*     */   private final File rClassSource;
/*     */   private final File staticLibApk;
/*     */   private final File rDotTxt;
/*     */   
/*     */   public LinkLibraryAndroidResourcesTask$ConfigAction(@NotNull VariantScope scope, @Nullable File rClassSource, @NotNull File staticLibApk, @NotNull File rDotTxt)
/*     */   {
/* 110 */     this.scope = scope;this.rClassSource = rClassSource;this.staticLibApk = staticLibApk;this.rDotTxt = rDotTxt;
/*     */   }
/*     */   
/*     */   @NotNull
/* 116 */   public String getName() { return scope.getTaskName("link", "Resources"); }
/*     */   @NotNull
/* 118 */   public Class<LinkLibraryAndroidResourcesTask> getType() { return LinkLibraryAndroidResourcesTask.class; }
/*     */   
/*     */   /* Error */
/*     */   public void execute(@NotNull LinkLibraryAndroidResourcesTask task)
/*     */   {
/*     */     // Byte code:
/*     */     //   0: aload_1
/*     */     //   1: ldc 37
/*     */     //   3: invokestatic 43	kotlin/jvm/internal/Intrinsics:checkParameterIsNotNull	(Ljava/lang/Object;Ljava/lang/String;)V
/*     */     //   6: aload_1
/*     */     //   7: aload_0
/*     */     //   8: getfield 14	com/android/build/gradle/internal/res/namespaced/LinkLibraryAndroidResourcesTask$ConfigAction:scope	Lcom/android/build/gradle/internal/scope/VariantScope;
/*     */     //   11: invokeinterface 46 1 0
/*     */     //   16: invokevirtual 50	com/android/build/gradle/internal/res/namespaced/LinkLibraryAndroidResourcesTask:setVariantName	(Ljava/lang/String;)V
/*     */     //   19: aload_1
/*     */     //   20: aload_0
/*     */     //   21: getfield 14	com/android/build/gradle/internal/res/namespaced/LinkLibraryAndroidResourcesTask$ConfigAction:scope	Lcom/android/build/gradle/internal/scope/VariantScope;
/*     */     //   24: getstatic 56	com/android/build/gradle/internal/scope/TaskOutputHolder$TaskOutputType:AAPT_FRIENDLY_MERGED_MANIFESTS	Lcom/android/build/gradle/internal/scope/TaskOutputHolder$TaskOutputType;
/*     */     //   27: checkcast 58	com/android/build/gradle/internal/scope/TaskOutputHolder$OutputType
/*     */     //   30: invokeinterface 62 2 0
/*     */     //   35: ifeq +27 -> 62
/*     */     //   38: aload_0
/*     */     //   39: getfield 14	com/android/build/gradle/internal/res/namespaced/LinkLibraryAndroidResourcesTask$ConfigAction:scope	Lcom/android/build/gradle/internal/scope/VariantScope;
/*     */     //   42: getstatic 56	com/android/build/gradle/internal/scope/TaskOutputHolder$TaskOutputType:AAPT_FRIENDLY_MERGED_MANIFESTS	Lcom/android/build/gradle/internal/scope/TaskOutputHolder$TaskOutputType;
/*     */     //   45: checkcast 58	com/android/build/gradle/internal/scope/TaskOutputHolder$OutputType
/*     */     //   48: invokeinterface 66 2 0
/*     */     //   53: dup
/*     */     //   54: ldc 68
/*     */     //   56: invokestatic 71	kotlin/jvm/internal/Intrinsics:checkExpressionValueIsNotNull	(Ljava/lang/Object;Ljava/lang/String;)V
/*     */     //   59: goto +24 -> 83
/*     */     //   62: aload_0
/*     */     //   63: getfield 14	com/android/build/gradle/internal/res/namespaced/LinkLibraryAndroidResourcesTask$ConfigAction:scope	Lcom/android/build/gradle/internal/scope/VariantScope;
/*     */     //   66: getstatic 74	com/android/build/gradle/internal/scope/TaskOutputHolder$TaskOutputType:MERGED_MANIFESTS	Lcom/android/build/gradle/internal/scope/TaskOutputHolder$TaskOutputType;
/*     */     //   69: checkcast 58	com/android/build/gradle/internal/scope/TaskOutputHolder$OutputType
/*     */     //   72: invokeinterface 66 2 0
/*     */     //   77: dup
/*     */     //   78: ldc 76
/*     */     //   80: invokestatic 71	kotlin/jvm/internal/Intrinsics:checkExpressionValueIsNotNull	(Ljava/lang/Object;Ljava/lang/String;)V
/*     */     //   83: invokestatic 80	com/android/build/gradle/internal/res/namespaced/LinkLibraryAndroidResourcesTask:access$setManifestFileDirectory$p	(Lcom/android/build/gradle/internal/res/namespaced/LinkLibraryAndroidResourcesTask;Lorg/gradle/api/file/FileCollection;)V
/*     */     //   86: aload_1
/*     */     //   87: aload_0
/*     */     //   88: getfield 14	com/android/build/gradle/internal/res/namespaced/LinkLibraryAndroidResourcesTask$ConfigAction:scope	Lcom/android/build/gradle/internal/scope/VariantScope;
/*     */     //   91: getstatic 83	com/android/build/gradle/internal/scope/TaskOutputHolder$TaskOutputType:RES_COMPILED_FLAT_FILES	Lcom/android/build/gradle/internal/scope/TaskOutputHolder$TaskOutputType;
/*     */     //   94: checkcast 58	com/android/build/gradle/internal/scope/TaskOutputHolder$OutputType
/*     */     //   97: invokeinterface 66 2 0
/*     */     //   102: dup
/*     */     //   103: ldc 85
/*     */     //   105: invokestatic 71	kotlin/jvm/internal/Intrinsics:checkExpressionValueIsNotNull	(Ljava/lang/Object;Ljava/lang/String;)V
/*     */     //   108: invokestatic 88	com/android/build/gradle/internal/res/namespaced/LinkLibraryAndroidResourcesTask:access$setInputResourcesDirectories$p	(Lcom/android/build/gradle/internal/res/namespaced/LinkLibraryAndroidResourcesTask;Lorg/gradle/api/file/FileCollection;)V
/*     */     //   111: aload_1
/*     */     //   112: aload_0
/*     */     //   113: getfield 14	com/android/build/gradle/internal/res/namespaced/LinkLibraryAndroidResourcesTask$ConfigAction:scope	Lcom/android/build/gradle/internal/scope/VariantScope;
/*     */     //   116: getstatic 94	com/android/build/gradle/internal/publishing/AndroidArtifacts$ConsumedConfigType:COMPILE_CLASSPATH	Lcom/android/build/gradle/internal/publishing/AndroidArtifacts$ConsumedConfigType;
/*     */     //   119: getstatic 100	com/android/build/gradle/internal/publishing/AndroidArtifacts$ArtifactScope:ALL	Lcom/android/build/gradle/internal/publishing/AndroidArtifacts$ArtifactScope;
/*     */     //   122: getstatic 106	com/android/build/gradle/internal/publishing/AndroidArtifacts$ArtifactType:RES_STATIC_LIBRARY	Lcom/android/build/gradle/internal/publishing/AndroidArtifacts$ArtifactType;
/*     */     //   125: invokeinterface 110 4 0
/*     */     //   130: dup
/*     */     //   131: ldc 112
/*     */     //   133: invokestatic 71	kotlin/jvm/internal/Intrinsics:checkExpressionValueIsNotNull	(Ljava/lang/Object;Ljava/lang/String;)V
/*     */     //   136: invokestatic 115	com/android/build/gradle/internal/res/namespaced/LinkLibraryAndroidResourcesTask:access$setLibraryDependencies$p	(Lcom/android/build/gradle/internal/res/namespaced/LinkLibraryAndroidResourcesTask;Lorg/gradle/api/file/FileCollection;)V
/*     */     //   139: aload_1
/*     */     //   140: aload_0
/*     */     //   141: getfield 14	com/android/build/gradle/internal/res/namespaced/LinkLibraryAndroidResourcesTask$ConfigAction:scope	Lcom/android/build/gradle/internal/scope/VariantScope;
/*     */     //   144: getstatic 94	com/android/build/gradle/internal/publishing/AndroidArtifacts$ConsumedConfigType:COMPILE_CLASSPATH	Lcom/android/build/gradle/internal/publishing/AndroidArtifacts$ConsumedConfigType;
/*     */     //   147: getstatic 100	com/android/build/gradle/internal/publishing/AndroidArtifacts$ArtifactScope:ALL	Lcom/android/build/gradle/internal/publishing/AndroidArtifacts$ArtifactScope;
/*     */     //   150: getstatic 118	com/android/build/gradle/internal/publishing/AndroidArtifacts$ArtifactType:RES_SHARED_STATIC_LIBRARY	Lcom/android/build/gradle/internal/publishing/AndroidArtifacts$ArtifactType;
/*     */     //   153: invokeinterface 110 4 0
/*     */     //   158: dup
/*     */     //   159: ldc 120
/*     */     //   161: invokestatic 71	kotlin/jvm/internal/Intrinsics:checkExpressionValueIsNotNull	(Ljava/lang/Object;Ljava/lang/String;)V
/*     */     //   164: invokestatic 123	com/android/build/gradle/internal/res/namespaced/LinkLibraryAndroidResourcesTask:access$setSharedLibraryDependencies$p	(Lcom/android/build/gradle/internal/res/namespaced/LinkLibraryAndroidResourcesTask;Lorg/gradle/api/file/FileCollection;)V
/*     */     //   167: aload_0
/*     */     //   168: getfield 14	com/android/build/gradle/internal/res/namespaced/LinkLibraryAndroidResourcesTask$ConfigAction:scope	Lcom/android/build/gradle/internal/scope/VariantScope;
/*     */     //   171: invokeinterface 127 1 0
/*     */     //   176: dup
/*     */     //   177: ldc -127
/*     */     //   179: invokestatic 71	kotlin/jvm/internal/Intrinsics:checkExpressionValueIsNotNull	(Ljava/lang/Object;Ljava/lang/String;)V
/*     */     //   182: invokevirtual 134	com/android/build/gradle/internal/variant/BaseVariantData:getType	()Lcom/android/builder/core/VariantType;
/*     */     //   185: getstatic 140	com/android/builder/core/VariantType:FEATURE	Lcom/android/builder/core/VariantType;
/*     */     //   188: invokestatic 144	kotlin/jvm/internal/Intrinsics:areEqual	(Ljava/lang/Object;Ljava/lang/Object;)Z
/*     */     //   191: ifeq +37 -> 228
/*     */     //   194: aload_0
/*     */     //   195: getfield 14	com/android/build/gradle/internal/res/namespaced/LinkLibraryAndroidResourcesTask$ConfigAction:scope	Lcom/android/build/gradle/internal/scope/VariantScope;
/*     */     //   198: invokeinterface 148 1 0
/*     */     //   203: ifne +25 -> 228
/*     */     //   206: aload_1
/*     */     //   207: aload_0
/*     */     //   208: getfield 14	com/android/build/gradle/internal/res/namespaced/LinkLibraryAndroidResourcesTask$ConfigAction:scope	Lcom/android/build/gradle/internal/scope/VariantScope;
/*     */     //   211: getstatic 94	com/android/build/gradle/internal/publishing/AndroidArtifacts$ConsumedConfigType:COMPILE_CLASSPATH	Lcom/android/build/gradle/internal/publishing/AndroidArtifacts$ConsumedConfigType;
/*     */     //   214: getstatic 151	com/android/build/gradle/internal/publishing/AndroidArtifacts$ArtifactScope:MODULE	Lcom/android/build/gradle/internal/publishing/AndroidArtifacts$ArtifactScope;
/*     */     //   217: getstatic 154	com/android/build/gradle/internal/publishing/AndroidArtifacts$ArtifactType:FEATURE_RESOURCE_PKG	Lcom/android/build/gradle/internal/publishing/AndroidArtifacts$ArtifactType;
/*     */     //   220: invokeinterface 110 4 0
/*     */     //   225: invokestatic 157	com/android/build/gradle/internal/res/namespaced/LinkLibraryAndroidResourcesTask:access$setFeatureDependencies$p	(Lcom/android/build/gradle/internal/res/namespaced/LinkLibraryAndroidResourcesTask;Lorg/gradle/api/file/FileCollection;)V
/*     */     //   228: aload_0
/*     */     //   229: getfield 14	com/android/build/gradle/internal/res/namespaced/LinkLibraryAndroidResourcesTask$ConfigAction:scope	Lcom/android/build/gradle/internal/scope/VariantScope;
/*     */     //   232: invokeinterface 160 1 0
/*     */     //   237: dup
/*     */     //   238: ifnull +9 -> 247
/*     */     //   241: invokevirtual 164	com/android/build/gradle/internal/variant/BaseVariantData:getScope	()Lcom/android/build/gradle/internal/scope/VariantScope;
/*     */     //   244: goto +5 -> 249
/*     */     //   247: pop
/*     */     //   248: aconst_null
/*     */     //   249: astore_2
/*     */     //   250: aload_2
/*     */     //   251: ifnull +19 -> 270
/*     */     //   254: aload_1
/*     */     //   255: aload_2
/*     */     //   256: getstatic 166	com/android/build/gradle/internal/scope/TaskOutputHolder$TaskOutputType:RES_STATIC_LIBRARY	Lcom/android/build/gradle/internal/scope/TaskOutputHolder$TaskOutputType;
/*     */     //   259: checkcast 58	com/android/build/gradle/internal/scope/TaskOutputHolder$OutputType
/*     */     //   262: invokeinterface 66 2 0
/*     */     //   267: invokestatic 169	com/android/build/gradle/internal/res/namespaced/LinkLibraryAndroidResourcesTask:access$setTested$p	(Lcom/android/build/gradle/internal/res/namespaced/LinkLibraryAndroidResourcesTask;Lorg/gradle/api/file/FileCollection;)V
/*     */     //   270: aload_1
/*     */     //   271: aload_0
/*     */     //   272: getfield 14	com/android/build/gradle/internal/res/namespaced/LinkLibraryAndroidResourcesTask$ConfigAction:scope	Lcom/android/build/gradle/internal/scope/VariantScope;
/*     */     //   275: invokeinterface 173 1 0
/*     */     //   280: dup
/*     */     //   281: ldc -81
/*     */     //   283: invokestatic 71	kotlin/jvm/internal/Intrinsics:checkExpressionValueIsNotNull	(Ljava/lang/Object;Ljava/lang/String;)V
/*     */     //   286: invokevirtual 181	com/android/build/gradle/internal/scope/GlobalScope:getIntermediatesDir	()Ljava/io/File;
/*     */     //   289: iconst_2
/*     */     //   290: anewarray 183	java/lang/String
/*     */     //   293: dup
/*     */     //   294: iconst_0
/*     */     //   295: ldc -71
/*     */     //   297: aastore
/*     */     //   298: dup
/*     */     //   299: iconst_1
/*     */     //   300: aload_0
/*     */     //   301: getfield 14	com/android/build/gradle/internal/res/namespaced/LinkLibraryAndroidResourcesTask$ConfigAction:scope	Lcom/android/build/gradle/internal/scope/VariantScope;
/*     */     //   304: invokeinterface 189 1 0
/*     */     //   309: dup
/*     */     //   310: ldc -65
/*     */     //   312: invokestatic 71	kotlin/jvm/internal/Intrinsics:checkExpressionValueIsNotNull	(Ljava/lang/Object;Ljava/lang/String;)V
/*     */     //   315: invokevirtual 196	com/android/build/gradle/internal/core/GradleVariantConfiguration:getDirName	()Ljava/lang/String;
/*     */     //   318: aastore
/*     */     //   319: invokestatic 202	com/android/utils/FileUtils:join	(Ljava/io/File;[Ljava/lang/String;)Ljava/io/File;
/*     */     //   322: dup
/*     */     //   323: ldc -52
/*     */     //   325: invokestatic 71	kotlin/jvm/internal/Intrinsics:checkExpressionValueIsNotNull	(Ljava/lang/Object;Ljava/lang/String;)V
/*     */     //   328: invokestatic 208	com/android/build/gradle/internal/res/namespaced/LinkLibraryAndroidResourcesTask:access$setAaptIntermediateDir$p	(Lcom/android/build/gradle/internal/res/namespaced/LinkLibraryAndroidResourcesTask;Ljava/io/File;)V
/*     */     //   331: aload_1
/*     */     //   332: aload_0
/*     */     //   333: getfield 212	com/android/build/gradle/internal/res/namespaced/LinkLibraryAndroidResourcesTask$ConfigAction:rClassSource	Ljava/io/File;
/*     */     //   336: invokestatic 215	com/android/build/gradle/internal/res/namespaced/LinkLibraryAndroidResourcesTask:access$setRClassSource$p	(Lcom/android/build/gradle/internal/res/namespaced/LinkLibraryAndroidResourcesTask;Ljava/io/File;)V
/*     */     //   339: aload_1
/*     */     //   340: aload_0
/*     */     //   341: getfield 218	com/android/build/gradle/internal/res/namespaced/LinkLibraryAndroidResourcesTask$ConfigAction:staticLibApk	Ljava/io/File;
/*     */     //   344: invokestatic 221	com/android/build/gradle/internal/res/namespaced/LinkLibraryAndroidResourcesTask:access$setStaticLibApk$p	(Lcom/android/build/gradle/internal/res/namespaced/LinkLibraryAndroidResourcesTask;Ljava/io/File;)V
/*     */     //   347: aload_1
/*     */     //   348: aload_0
/*     */     //   349: getfield 14	com/android/build/gradle/internal/res/namespaced/LinkLibraryAndroidResourcesTask$ConfigAction:scope	Lcom/android/build/gradle/internal/scope/VariantScope;
/*     */     //   352: invokeinterface 173 1 0
/*     */     //   357: dup
/*     */     //   358: ldc -81
/*     */     //   360: invokestatic 71	kotlin/jvm/internal/Intrinsics:checkExpressionValueIsNotNull	(Ljava/lang/Object;Ljava/lang/String;)V
/*     */     //   363: invokevirtual 225	com/android/build/gradle/internal/scope/GlobalScope:getAndroidBuilder	()Lcom/android/builder/core/AndroidBuilder;
/*     */     //   366: invokevirtual 229	com/android/build/gradle/internal/res/namespaced/LinkLibraryAndroidResourcesTask:setAndroidBuilder	(Lcom/android/builder/core/AndroidBuilder;)V
/*     */     //   369: aload_1
/*     */     //   370: new 231	com/android/build/gradle/internal/res/namespaced/LinkLibraryAndroidResourcesTask$ConfigAction$execute$1
/*     */     //   373: dup
/*     */     //   374: aload_0
/*     */     //   375: getfield 14	com/android/build/gradle/internal/res/namespaced/LinkLibraryAndroidResourcesTask$ConfigAction:scope	Lcom/android/build/gradle/internal/scope/VariantScope;
/*     */     //   378: invokeinterface 189 1 0
/*     */     //   383: invokespecial 235	com/android/build/gradle/internal/res/namespaced/LinkLibraryAndroidResourcesTask$ConfigAction$execute$1:<init>	(Lcom/android/build/gradle/internal/core/GradleVariantConfiguration;)V
/*     */     //   386: checkcast 237	kotlin/jvm/functions/Function0
/*     */     //   389: astore_3
/*     */     //   390: new 239	com/android/build/gradle/internal/res/namespaced/LinkLibraryAndroidResourcesTaskKt$sam$Supplier$207e2d1c
/*     */     //   393: dup
/*     */     //   394: aload_3
/*     */     //   395: invokespecial 242	com/android/build/gradle/internal/res/namespaced/LinkLibraryAndroidResourcesTaskKt$sam$Supplier$207e2d1c:<init>	(Lkotlin/jvm/functions/Function0;)V
/*     */     //   398: checkcast 244	com/google/common/base/Supplier
/*     */     //   401: invokestatic 250	com/google/common/base/Suppliers:memoize	(Lcom/google/common/base/Supplier;)Lcom/google/common/base/Supplier;
/*     */     //   404: dup
/*     */     //   405: ldc -4
/*     */     //   407: invokestatic 71	kotlin/jvm/internal/Intrinsics:checkExpressionValueIsNotNull	(Ljava/lang/Object;Ljava/lang/String;)V
/*     */     //   410: checkcast 254	java/util/function/Supplier
/*     */     //   413: invokestatic 258	com/android/build/gradle/internal/res/namespaced/LinkLibraryAndroidResourcesTask:access$setPackageForRSupplier$p	(Lcom/android/build/gradle/internal/res/namespaced/LinkLibraryAndroidResourcesTask;Ljava/util/function/Supplier;)V
/*     */     //   416: aload_1
/*     */     //   417: aload_0
/*     */     //   418: getfield 261	com/android/build/gradle/internal/res/namespaced/LinkLibraryAndroidResourcesTask$ConfigAction:rDotTxt	Ljava/io/File;
/*     */     //   421: invokestatic 264	com/android/build/gradle/internal/res/namespaced/LinkLibraryAndroidResourcesTask:access$setRDotTxt$p	(Lcom/android/build/gradle/internal/res/namespaced/LinkLibraryAndroidResourcesTask;Ljava/io/File;)V
/*     */     //   424: return
/*     */     // Line number table:
/*     */     //   Java source line #121	-> byte code offset #6
/*     */     //   Java source line #122	-> byte code offset #19
/*     */     //   Java source line #123	-> byte code offset #19
/*     */     //   Java source line #124	-> byte code offset #38
/*     */     //   Java source line #126	-> byte code offset #62
/*     */     //   Java source line #123	-> byte code offset #83
/*     */     //   Java source line #128	-> byte code offset #86
/*     */     //   Java source line #129	-> byte code offset #111
/*     */     //   Java source line #130	-> byte code offset #111
/*     */     //   Java source line #131	-> byte code offset #116
/*     */     //   Java source line #132	-> byte code offset #119
/*     */     //   Java source line #133	-> byte code offset #122
/*     */     //   Java source line #130	-> byte code offset #125
/*     */     //   Java source line #134	-> byte code offset #139
/*     */     //   Java source line #135	-> byte code offset #139
/*     */     //   Java source line #136	-> byte code offset #144
/*     */     //   Java source line #137	-> byte code offset #147
/*     */     //   Java source line #138	-> byte code offset #150
/*     */     //   Java source line #135	-> byte code offset #153
/*     */     //   Java source line #140	-> byte code offset #167
/*     */     //   Java source line #141	-> byte code offset #206
/*     */     //   Java source line #142	-> byte code offset #206
/*     */     //   Java source line #143	-> byte code offset #211
/*     */     //   Java source line #144	-> byte code offset #214
/*     */     //   Java source line #145	-> byte code offset #217
/*     */     //   Java source line #142	-> byte code offset #220
/*     */     //   Java source line #148	-> byte code offset #228
/*     */     //   Java source line #149	-> byte code offset #250
/*     */     //   Java source line #150	-> byte code offset #254
/*     */     //   Java source line #153	-> byte code offset #270
/*     */     //   Java source line #154	-> byte code offset #270
/*     */     //   Java source line #155	-> byte code offset #271
/*     */     //   Java source line #154	-> byte code offset #319
/*     */     //   Java source line #156	-> byte code offset #331
/*     */     //   Java source line #157	-> byte code offset #339
/*     */     //   Java source line #158	-> byte code offset #347
/*     */     //   Java source line #159	-> byte code offset #369
/*     */     //   Java source line #160	-> byte code offset #416
/*     */     //   Java source line #161	-> byte code offset #424
/*     */     // Local variable table:
/*     */     //   start	length	slot	name	signature
/*     */     //   0	425	0	this	ConfigAction
/*     */     //   0	425	1	task	LinkLibraryAndroidResourcesTask
/*     */     //   250	175	2	testedScope	VariantScope
/*     */   }
/*     */ }

/* Location:
 * Qualified Name:     com.android.build.gradle.internal.res.namespaced.LinkLibraryAndroidResourcesTask.ConfigAction
 * Java Class Version: 8 (52.0)
 * JD-Core Version:    0.7.1
 */